PUCHIK/__init__.py
PUCHIK/_version.py
PUCHIK/grid_project/__init__.py
PUCHIK/grid_project/settings.py
PUCHIK/grid_project/alpha_shaper/AlphaShaper.exe
PUCHIK/grid_project/alpha_shaper/gmp-10.dll
PUCHIK/grid_project/alpha_shaper/src/main.cpp
PUCHIK/grid_project/core/AlphaShape.py
PUCHIK/grid_project/core/__init__.py
PUCHIK/grid_project/core/interface.py
PUCHIK/grid_project/core/pyutils.py
PUCHIK/grid_project/core/utils.c
PUCHIK/grid_project/core/utils.cp310-win_amd64.pyd
PUCHIK/grid_project/core/utils.cp311-win_amd64.pyd
PUCHIK/grid_project/core/utils.pyx
PUCHIK/grid_project/utilities/MoleculeSystem.py
PUCHIK/grid_project/utilities/__init__.py
PUCHIK/grid_project/utilities/decorators.py
PUCHIK/grid_project/utilities/universal_objects.py
PUCHIK/grid_project/volume/__init__.py
PUCHIK/grid_project/volume/monte_carlo.py
PUCHIK/test/__init__.py
PUCHIK/test/test_interface.py
puchik-1.2.5.dist-info/licenses/LICENSE
puchik-1.2.5.dist-info/METADATA
puchik-1.2.5.dist-info/WHEEL
puchik-1.2.5.dist-info/top_level.txt
puchik-1.2.5.dist-info/RECORD
