Metadata-Version: 2.4
Name: PUCHIK
Version: 1.2.5
Summary: Python Utility for Characterizing Heterogeneous Interfaces and Kinetics creates a grid from an molecular dynamics structure file. The system in question can have an arbitrary structure. Volume and species densities can then calculated.
Home-page: https://github.com/hrachishkhanyan/grid_project
Author: H. Ishkhanyan
Author-email: Hrachya Ishkhanyan <hrachya.ishkhanyan@kcl.ac.uk>
License: MIT License
Project-URL: Homepage, https://github.com/hrachishkhanyan/grid_project
Project-URL: Bug Tracker, https://github.com/hrachishkhanyan/grid_project/issues
Classifier: Programming Language :: Python :: 3
Classifier: License :: OSI Approved :: MIT License
Classifier: Operating System :: OS Independent
Provides: PUCHIK
Requires-Python: >=3.10
License-File: LICENSE
Requires-Dist: MDAnalysis
Requires-Dist: scipy>=1.14.0
Requires-Dist: PyGEL3D
Requires-Dist: python-dotenv
Dynamic: author
Dynamic: home-page
Dynamic: license-file
Dynamic: provides
